mp3p/__init__.py
mp3p/__main__.py
mp3p/command_player.py
mp3p/controls.py
mp3p/time_manipulation.py
mp3p/time_util.py
mp3p/volume.py
mp3p-1.0.1.dist-info/METADATA
mp3p-1.0.1.dist-info/WHEEL
mp3p-1.0.1.dist-info/entry_points.txt
mp3p-1.0.1.dist-info/top_level.txt
mp3p-1.0.1.dist-info/RECORD
