Metadata-Version: 2.1
Name: mp3p
Version: 1.0.1
Summary: Play mp3 files over the commandline
Home-page: UNKNOWN
Author: Josiah Bennett
Author-email: josiah.bennett@web.de
License: MIT
Platform: UNKNOWN
Classifier: License :: OSI Approved :: MIT License
Classifier: Programming Language :: Python :: 3
Classifier: Programming Language :: Python :: 3.8
Requires-Dist: python-vlc
